nonebot_plugin_mcqq/__init__.py
nonebot_plugin_mcqq/bot_manage.py
nonebot_plugin_mcqq/config.py
nonebot_plugin_mcqq/data_source.py
nonebot_plugin_mcqq/on_minecraft_msg.py
nonebot_plugin_mcqq/on_qq_msg.py
nonebot_plugin_mcqq/resource/bg.png
nonebot_plugin_mcqq/resource/unifont-15.0.01.ttf
nonebot_plugin_mcqq/utils/__init__.py
nonebot_plugin_mcqq/utils/draw_result.py
nonebot_plugin_mcqq/utils/parse_qq_msg.py
nonebot_plugin_mcqq/utils/qq_util.py
nonebot_plugin_mcqq/utils/rule.py
nonebot_plugin_mcqq/utils/send_to_mc.py
nonebot_plugin_mcqq/utils/send_to_qq.py
nonebot_plugin_mcqq-2.8.0.dist-info/METADATA
nonebot_plugin_mcqq-2.8.0.dist-info/WHEEL
nonebot_plugin_mcqq-2.8.0.dist-info/licenses/LICENSE
nonebot_plugin_mcqq-2.8.0.dist-info/RECORD
