Metadata-Version: 2.4
Name: nonebot-plugin-mcqq
Version: 2.8.0
Summary: 基于NoneBot的QQ群聊与Minecraft Server消息互通插件
Author-email: 17TheWord <17theword@gmail.com>
License-Expression: MIT
License-File: LICENSE
Requires-Python: <4,>=3.10
Requires-Dist: nonebot-adapter-minecraft>=1.7.1
Requires-Dist: nonebot-adapter-onebot>=2.4.6
Requires-Dist: nonebot-adapter-qq>=1.6.5
Requires-Dist: nonebot2[fastapi,httpx,websockets]>=2.4.3
Provides-Extra: pil
Requires-Dist: pillow>=11.3.0; extra == 'pil'
